{"nodes": [{"id": "comparative_code_pipeline", "label": "Comparative Code Analysis Pipeline: Source Code -> ROSE AST -> Deep Representation Learning -> Neural Network Prediction", "file_type": "image", "source_file": "images/projects/comparative_code.png", "source_location": null, "source_url": null, "captured_at": null, "author": null, "contributor": null}, {"id": "comparative_code_rose", "label": "ROSE Compiler Framework for AST Generation", "file_type": "rationale", "source_file": "images/projects/comparative_code.png", "source_location": null, "source_url": null, "captured_at": null, "author": null, "contributor": null}, {"id": "comparative_code_deep_learning", "label": "Deep Representation Learning from AST (Node Rep -> Code Rep)", "file_type": "rationale", "source_file": "images/projects/comparative_code.png", "source_location": null, "source_url": null, "captured_at": null, "author": null, "contributor": null}], "edges": [{"source": "comparative_code_pipeline", "target": "comparative_code_rose", "relation": "implements", "confidence": "EXTRACTED", "confidence_score": 1.0, "source_file": "images/projects/comparative_code.png", "source_location": null, "weight": 1.0}, {"source": "comparative_code_pipeline", "target": "comparative_code_deep_learning", "relation": "implements", "confidence": "EXTRACTED", "confidence_score": 1.0, "source_file": "images/projects/comparative_code.png", "source_location": null, "weight": 1.0}, {"source": "comparative_code_rose", "target": "comparative_code_deep_learning", "relation": "shares_data_with", "confidence": "EXTRACTED", "confidence_score": 1.0, "source_file": "images/projects/comparative_code.png", "source_location": null, "weight": 1.0}], "hyperedges": []}